markusapi/__init__.py
markusapi/markusapi.py
markusapi/response_parser.py
markusapi/tests/__init__.py
markusapi/tests/test_markusapi.py
markusapi-0.3.0.dist-info/LICENSE
markusapi-0.3.0.dist-info/METADATA
markusapi-0.3.0.dist-info/WHEEL
markusapi-0.3.0.dist-info/top_level.txt
markusapi-0.3.0.dist-info/RECORD
