Metadata-Version: 2.1
Name: markusapi
Version: 0.3.0
Summary: Interface to interact with MarkUs API
Home-page: https://github.com/MarkUsProject/markus-api
Author: Alessio Di Sandro, Misha Schwartz, Sam Maldonado
Author-email: mschwa@cs.toronto.edu
License: UNKNOWN
Platform: UNKNOWN
Classifier: Programming Language :: Python :: 3
Classifier: License :: OSI Approved :: MIT License
Classifier: Operating System :: OS Independent
License-File: LICENSE
Requires-Dist: requests (==2.24.0)
